{"parent":"item/handheld","textures":{"layer0":"item/golden_sword"},"overrides":[
{"predicate":{"custom_model_data":1},"model":"asurvival:item/grass_mesh"},
{"predicate":{"custom_model_data":2},"model":"asurvival:item/empty_canteen"},
{"predicate":{"custom_model_data":3},"model":"asurvival:item/canteen"},
{"predicate":{"custom_model_data":4},"model":"asurvival:item/flower_bouquet"},
{"predicate":{"custom_model_data":5},"model":"asurvival:item/flint_knife"},
{"predicate":{"custom_model_data":6},"model":"asurvival:item/water_gun"},
{"predicate":{"custom_model_data":7},"model":"asurvival:item/slime_gun"},
{"predicate":{"custom_model_data":8},"model":"asurvival:item/blazing_ghastmallow"},
{"predicate":{"custom_model_data":9},"model":"asurvival:item/copper_bucket"},
{"predicate":{"custom_model_data":10},"model":"asurvival:item/tin_bucket"},
{"predicate":{"custom_model_data":11},"model":"asurvival:item/gloves/leather_gloves"},
{"predicate":{"custom_model_data":12},"model":"asurvival:item/bellows"},
{"predicate":{"custom_model_data":13},"model":"asurvival:item/hearth"},
{"predicate":{"custom_model_data":14},"model":"asurvival:item/food/bitten_cake_1"},
{"predicate":{"custom_model_data":15},"model":"asurvival:item/food/bitten_cake_2"},
{"predicate":{"custom_model_data":16},"model":"asurvival:item/food/bitten_cake_3"},
{"predicate":{"custom_model_data":17},"model":"asurvival:item/food/bitten_cake_4"},
{"predicate":{"custom_model_data":18},"model":"asurvival:item/food/bitten_cake_5"},
{"predicate":{"custom_model_data":19},"model":"asurvival:item/food/bitten_cake_6"},
{"predicate":{"custom_model_data":20},"model":"asurvival:item/brush"},
{"predicate":{"custom_model_data":21},"model":"asurvival:item/iron_knife"},
{"predicate":{"custom_model_data":22},"model":"asurvival:item/ice_axe"}
]}